Workbook

Sheet Sheet1
D2: Year
D3: 0 | E3: =+D3+1 -> 1 | F3: =+E3+1 -> 2 | G3: =+F3+1 -> 3 | H3: =+G3+1 -> 4 | I3: =+H3+1 -> 5 | J3: =+I3+1 -> 6
C4: Gross Revenue | D4: 967000 | E4: =+D4*(1+E5) -> 967000 | F4: =+E4*(1+F5) -> 996010 | G4: =+F4*(1+G5) -> 1025890.3 | H4: =+G4*(1+H5) -> 1056667 | I4: =+H4*(1+I5) -> 1088367 | J4: =+I4*(1+J5) -> 1121018
C5: Revenue Growth | E5: 0 | F5: 0.03 | G5: 0.03 | H5: 0.03 | I5: 0.03 | J5: 0.03
C6: Average | E6: 0.0275 | F6: 0.0275 | G6: 0.0275 | H6: 0.0275 | I6: 0.0275 | J6: 0.0275
C8: Commission | E8: =+E4*E9 -> 477910.74 | F8: =+F4*F9 -> 492248.06 | G8: =+G4*G9 -> 507015.5 | H8: =+H4*H9 -> 522225.97 | I8: =+I4*I9 -> 537892.75 | J8: =+J4*J9 -> 554029.53
E9: =+SUMPRODUCT(D13:D20,D23:D30) -> 0.49422 | F9: =+$E$9 -> 0.49422 | G9: =+$E$9 -> 0.49422 | H9: =+$E$9 -> 0.49422 | I9: =+$E$9 -> 0.49422 | J9: =+$E$9 -> 0.49422
C12: Contract Commission Rates
C13: Labor Income | D13: 0.49
C14: Equipment Income | D14: 0.49
C15: Logistics Income | D15: 0.49
C16: Consumable / Sale Item Income | D16: 0.49
C17: Creative Content Income | D17: 0.3
C18: Rigging Income | D18: 0.3
C19: Power Income | D19: 0.75
C20: HSIA Icome | D20: 0.75
C22: Sales By Category
C23: Labor Income | D23: 0.4003
C24: Equipment Income | D24: 0.5611
C25: Logistics Income | D25: 0.0196
C26: Consumable / Sale Item Income | D26: 0
C27: Creative Content Income | D27: 0.0014
C28: Rigging Income | D28: 0.0002
C29: Power Income | D29: 0
C30: HSIA Icome | D30: 0.0174
C34: Net Revenue | E34: =+E4-E8 -> 489089.26 | F34: =+F4-F8 -> 503761.94 | G34: =+G4-G8 -> 518874.8 | H34: =+H4-H8 -> 534441.04 | I34: =+I4-I8 -> 550474.27 | J34: =+J4-J8 -> 566988.5
C36: COGS | E36: =+E34*E37 -> 48908.926 | F36: =+F34*F37 -> 50376.194 | G36: =+G34*G37 -> 51887.48 | H36: =+H34*H37 -> 53444.104 | I36: =+I34*I37 -> 55047.427 | J36: =+J34*J37 -> 56698.85
E37: 0.1 | F37: 0.1 | G37: 0.1 | H37: 0.1 | I37: 0.1 | J37: 0.1
C40: Payroll | E40: =+SUMIFS('Payroll Calculation'!H:H,'Payroll Calculation'!$B:$B,"Salary")+(($F$61*E4)+$F$62*(E4-E8)) -> 247731.23 | F40: =+SUMIFS('Payroll Calculation'!I:I,'Payroll Calculation'!$B:$B,"Salary")+(($F$61*F4)+$F$62*(F4-F8)) -> 255163.17 | G40: =+SUMIFS('Payroll Calculation'!J:J,'Payroll Calculation'!$B:$B,"Salary")+(($F$61*G4)+$F$62*(G4-G8)) -> 262818.06 | H40: =+SUMIFS('Payroll Calculation'!K:K,'Payroll Calculation'!$B:$B,"Salary")+(($F$61*H4)+$F$62*(H4-H8)) -> 270702.6 | I40: =+SUMIFS('Payroll Calculation'!L:L,'Payroll Calculation'!$B:$B,"Salary")+(($F$61*I4)+$F$62*(I4-I8)) -> 278823.68 | J40: =+SUMIFS('Payroll Calculation'!M:M,'Payroll Calculation'!$B:$B,"Salary")+(($F$61*J4)+$F$62*(J4-J8)) -> 287188.39
E41: =+E40/(E4-E8) -> 0.50651537 | F41: =+F40/(F4-F8) -> 0.50651537 | G41: =+G40/(G4-G8) -> 0.50651537 | H41: =+H40/(H4-H8) -> 0.50651537 | I41: =+I40/(I4-I8) -> 0.50651537 | J41: =+J40/(J4-J8) -> 0.50651537
C43: Merit Increase % | D43: 0.03
C45: Type | D45: Title | E45: Start Date | F45: Salary | G45: Salary w/Benefits
B46: 1 | C46: Salaried Full Time Staff | D46: Director | E46: -2 | F46: 78000 | G46: =+F46*(1+0.133) -> 88374
B47: =+B46+1 -> 2 | C47: Salaried Full Time Staff | D47: Technical Coordinator 1 | E47: -2 | F47: 55000 | G47: =+F47*(1+0.133) -> 62315
B48: =+B47+1 -> 3 | C48: Salaried Full Time Staff | D48: Technical Coordinator 2 | E48: -2 | F48: 0 | G48: =+F48*(1+0.133) -> 0
B49: =+B48+1 -> 4 | C49: Salaried Full Time Staff | D49: Technical Coordinator 3 | E49: -2 | F49: 0 | G49: =+F49*(1+0.133) -> 0
B50: =+B49+1 -> 5 | C50: Salaried Full Time Staff | D50: Technical Coordinator 4 | E50: -2 | F50: 0 | G50: =+F50*(1+0.133) -> 0
B51: =+B50+1 -> 6 | C51: Hourly Full Time Staff | D51: Technician 1 | E51: -2 | F51: 45670 | G51: =+F51*(1+0.133) -> 51744.11
B52: =+B51+1 -> 7 | C52: Hourly Full Time Staff | D52: Technician 2 | E52: -2 | F52: 0 | G52: =+F52*(1+0.133) -> 0
B53: =+B52+1 -> 8 | C53: Hourly Full Time Staff | D53: Technician 3 | E53: -2 | F53: 0 | G53: =+F53*(1+0.133) -> 0
B54: =+B53+1 -> 9 | C54: Hourly Full Time Staff | D54: Technician 4 | E54: -2 | F54: 0 | G54: =+F54*(1+0.133) -> 0
B55: =+B54+1 -> 10 | C55: Hourly Full Time Staff | D55: Technician 5 | E55: -2 | F55: 0 | G55: =+F55*(1+0.133) -> 0
B56: =+B55+1 -> 11 | C56: Hourly /Part Time / Seasonal Positions | D56: Technician 6 | E56: -2 | F56: 22880 | G56: =+F56*(1+8.85%) -> 24904.88
B57: =+B56+1 -> 12 | C57: Hourly /Part Time / Seasonal Positions | D57: Technician 7 | E57: -2 | F57: 0 | G57: =+F57*(1+8.85%) -> 0
B58: =+B57+1 -> 13 | C58: Hourly /Part Time / Seasonal Positions | D58: Technician 8 | E58: -2 | F58: 0 | G58: =+F58*(1+8.85%) -> 0
B59: =+B58+1 -> 14 | C59: Hourly /Part Time / Seasonal Positions | D59: Technician 9 | E59: -2 | F59: 0 | G59: =+F59*(1+8.85%) -> 0
C61: 60050 Incentives and Bonuses | F61: 0.016
C62: 60110 Profit Sharing | F62: 0.0089
C64: Signing Bonus Amortization | E64: =+$D$77/$J$3+E80 -> 10000 | F64: =+$D$77/$J$3+F80 -> 10000 | G64: =+$D$77/$J$3+G80 -> 10000 | H64: =+$D$77/$J$3+H80 -> 10000 | I64: =+$D$77/$J$3+I80 -> 10000 | J64: =+$D$77/$J$3+J80 -> 10000
C65: Expenses | E65: =+E34*E66 -> 31790.802 | F65: =+F34*F66 -> 32744.526 | G65: =+G34*G66 -> 33726.862 | H65: =+H34*H66 -> 34738.668 | I65: =+I34*I66 -> 35780.828 | J65: =+J34*J66 -> 36854.252
E66: 0.065 | F66: 0.065 | G66: 0.065 | H66: 0.065 | I66: 0.065 | J66: 0.065
C68: NOI | E68: =+E34-E36-E40-E65-E64 -> 150658.3 | F68: =+F34-F36-F40-F65-F64 -> 155478.05 | G68: =+G34-G36-G40-G65-G64 -> 160442.39 | H68: =+H34-H36-H40-H65-H64 -> 165555.67 | I68: =+I34-I36-I40-I65-I64 -> 170822.34 | J68: =+J34-J36-J40-J65-J64 -> 176247.01
E69: =+E68/E34 -> 0.30803846 | F69: =+F68/F34 -> 0.30863398 | G69: =+G68/G34 -> 0.30921215 | H69: =+H68/H34 -> 0.30977349 | I69: =+I68/I34 -> 0.31031847 | J69: =+J68/J34 -> 0.31084758
C72: Capex | D72: =+E4*D73 -> 243200.5 | E72: =+E73*E4 -> 0 | F72: =+F73*F4 -> 31374.315 | G72: =+G73*G4 -> 32315.544 | H72: =+H73*H4 -> 33285.011 | I72: =+I73*I4 -> 34283.561 | J72: =+J73*J4 -> 35312.068
D73: 0.2515 | E73: 0 | F73: 0.0315 | G73: 0.0315 | H73: 0.0315 | I73: 0.0315 | J73: 0.0315
C74: Payroll | D74: =+SUMIFS('Payroll Calculation'!$G$4:$G$155,'Payroll Calculation'!$B$4:$B$155,"Salary") -> 18944.833
C75: Expenses | D75: =+D76*E4 -> 6935.8531
D76: 0.0071725472
C77: Signing Bonus | D77: 60000
C78: Initial Investment | D78: =+D72+D74+D75+D77 -> 329081.19
C80: Signing Bonus | E80: 0 | F80: 0 | G80: 0 | H80: 0 | I80: 0 | J80: 0
C86: Net Cash | D86: =+D68-D78 -> -329081.19 | E86: =+E68-E72-E80+E64 -> 160658.3 | F86: =+F68-F72-F80+F64 -> 134103.74 | G86: =+G68-G72-G80+G64 -> 138126.85 | H86: =+H68-H72-H80+H64 -> 142270.65 | I86: =+I68-I72-I80+I64 -> 146538.77 | J86: =+J68-J72-J80+J64 -> 150934.94
C88: ROI | D88: =+RATE(6,,D86,SUM(D86:J86)) -> 0.087233978

Sheet Payroll Calculation
C3: Start Month | D3: Merit Increase | E3: Base Salary | G3: Year 0 | H3: Year 1 | I3: Year 2 | J3: Year 3 | K3: Year 4 | L3: Year 5 | M3: Year 6 | N3: Year 7 | O3: Year 8 | P3: Year 9 | Q3: Year 10
B4: Salary | C4: -1 | D4: =+Sheet1!$D$43 -> 0.03 | E4: =+Sheet1!$G$46 -> 88374 | G4: =E4*((1+D4)^G10*G11+(1+D4)^(G10+1)*G12)/12 -> 7364.5 | H4: =E4*((1+D4)^H10*H11+(1+D4)^(H10+1)*H12)/12 -> 88594.935 | I4: =E4*((1+D4)^I10*I11+(1+D4)^(I10+1)*I12)/12 -> 91252.783 | J4: =E4*((1+D4)^J10*J11+(1+D4)^(J10+1)*J12)/12 -> 93990.367 | K4: =E4*((1+D4)^K10*K11+(1+D4)^(K10+1)*K12)/12 -> 96810.078 | L4: =E4*((1+D4)^L10*L11+(1+D4)^(L10+1)*L12)/12 -> 99714.38 | M4: =E4*((1+D4)^M10*M11+(1+D4)^(M10+1)*M12)/12 -> 102705.81 | N4: =E4*((1+D4)^N10*N11+(1+D4)^(N10+1)*N12)/12 -> 105786.99 | O4: =E4*((1+D4)^O10*O11+(1+D4)^(O10+1)*O12)/12 -> 108960.6 | P4: =E4*((1+D4)^P10*P11+(1+D4)^(P10+1)*P12)/12 -> 112229.41 | Q4: =E4*((1+D4)^Q10*Q11+(1+D4)^(Q10+1)*Q12)/12 -> 115596.3
B5: Effective Annual Rate | G5: =IF(G6=0,0,G4/G6*12) -> 88374 | H5: =IF(H6=0,0,H4/H6*12) -> 88594.935 | I5: =IF(I6=0,0,I4/I6*12) -> 91252.783 | J5: =IF(J6=0,0,J4/J6*12) -> 93990.367 | K5: =IF(K6=0,0,K4/K6*12) -> 96810.078 | L5: =IF(L6=0,0,L4/L6*12) -> 99714.38 | M5: =IF(M6=0,0,M4/M6*12) -> 102705.81 | N5: =IF(N6=0,0,N4/N6*12) -> 105786.99 | ... Q5: =IF(Q6=0,0,Q4/Q6*12) -> 115596.3
B6: Months Worked | G6: =+G9-G8 -> 1 | H6: =+H9-H8 -> 12 | I6: =+I9-I8 -> 12 | J6: =+J9-J8 -> 12 | K6: =+K9-K8 -> 12 | L6: =+L9-L8 -> 12 | M6: =+M9-M8 -> 12 | N6: =+N9-N8 -> 12 | ... Q6: =+Q9-Q8 -> 12
B7: Year Index (n) | G7: 0 | H7: 1 | I7: 2 | J7: 3 | K7: 4 | L7: 5 | M7: 6 | N7: 7 | O7: 8 | P7: 9 | Q7: 10
B8: Service Months @ Yr Start | G8: =MAX(0,12*(G7-1)-C4) -> 0 | H8: =MAX(0,12*(H7-1)-C4) -> 1 | I8: =MAX(0,12*(I7-1)-C4) -> 13 | J8: =MAX(0,12*(J7-1)-C4) -> 25 | K8: =MAX(0,12*(K7-1)-C4) -> 37 | L8: =MAX(0,12*(L7-1)-C4) -> 49 | M8: =MAX(0,12*(M7-1)-C4) -> 61 | N8: =MAX(0,12*(N7-1)-C4) -> 73 | O8: =MAX(0,12*(O7-1)-C4) -> 85 | P8: =MAX(0,12*(P7-1)-C4) -> 97 | Q8: =MAX(0,12*(Q7-1)-C4) -> 109
B9: Service Months @ Yr End | G9: =MAX(0,12*G7-C4) -> 1 | H9: =MAX(0,12*H7-C4) -> 13 | I9: =MAX(0,12*I7-C4) -> 25 | J9: =MAX(0,12*J7-C4) -> 37 | K9: =MAX(0,12*K7-C4) -> 49 | L9: =MAX(0,12*L7-C4) -> 61 | M9: =MAX(0,12*M7-C4) -> 73 | N9: =MAX(0,12*N7-C4) -> 85 | O9: =MAX(0,12*O7-C4) -> 97 | P9: =MAX(0,12*P7-C4) -> 109 | Q9: =MAX(0,12*Q7-C4) -> 121
B10: Completed Service Yrs (k) | G10: =INT(G8/12) -> 0 | H10: =INT(H8/12) -> 0 | I10: =INT(I8/12) -> 1 | J10: =INT(J8/12) -> 2 | K10: =INT(K8/12) -> 3 | L10: =INT(L8/12) -> 4 | M10: =INT(M8/12) -> 5 | N10: =INT(N8/12) -> 6 | ... Q10: =INT(Q8/12) -> 9
B11: Months at Rate k | G11: =MIN(G9,12*(G10+1))-G8 -> 1 | H11: =MIN(H9,12*(H10+1))-H8 -> 11 | I11: =MIN(I9,12*(I10+1))-I8 -> 11 | J11: =MIN(J9,12*(J10+1))-J8 -> 11 | K11: =MIN(K9,12*(K10+1))-K8 -> 11 | L11: =MIN(L9,12*(L10+1))-L8 -> 11 | M11: =MIN(M9,12*(M10+1))-M8 -> 11 | N11: =MIN(N9,12*(N10+1))-N8 -> 11 | ... Q11: =MIN(Q9,12*(Q10+1))-Q8 -> 11
B12: Months at Rate k+1 | G12: =+G9-MIN(G9,12*(G10+1)) -> 0 | H12: =+H9-MIN(H9,12*(H10+1)) -> 1 | I12: =+I9-MIN(I9,12*(I10+1)) -> 1 | J12: =+J9-MIN(J9,12*(J10+1)) -> 1 | K12: =+K9-MIN(K9,12*(K10+1)) -> 1 | L12: =+L9-MIN(L9,12*(L10+1)) -> 1 | M12: =+M9-MIN(M9,12*(M10+1)) -> 1 | N12: =+N9-MIN(N9,12*(N10+1)) -> 1 | ... Q12: =+Q9-MIN(Q9,12*(Q10+1)) -> 1
C14: Start Month | D14: Merit Increase | E14: Base Salary | G14: Year 0 | H14: Year 1 | I14: Year 2 | J14: Year 3 | K14: Year 4 | L14: Year 5 | M14: Year 6 | N14: Year 7 | O14: Year 8 | P14: Year 9 | Q14: Year 10
B15: Salary | C15: -1 | D15: =+Sheet1!$D$43 -> 0.03 | E15: =+Sheet1!$G$47 -> 62315 | G15: =E15*((1+D15)^G21*G22+(1+D15)^(G21+1)*G23)/12 -> 5192.9167 | H15: =E15*((1+D15)^H21*H22+(1+D15)^(H21+1)*H23)/12 -> 62470.787 | I15: =E15*((1+D15)^I21*I22+(1+D15)^(I21+1)*I23)/12 -> 64344.911 | J15: =E15*((1+D15)^J21*J22+(1+D15)^(J21+1)*J23)/12 -> 66275.258 | K15: =E15*((1+D15)^K21*K22+(1+D15)^(K21+1)*K23)/12 -> 68263.516 | L15: =E15*((1+D15)^L21*L22+(1+D15)^(L21+1)*L23)/12 -> 70311.422 | M15: =E15*((1+D15)^M21*M22+(1+D15)^(M21+1)*M23)/12 -> 72420.764 | N15: =E15*((1+D15)^N21*N22+(1+D15)^(N21+1)*N23)/12 -> 74593.387 | O15: =E15*((1+D15)^O21*O22+(1+D15)^(O21+1)*O23)/12 -> 76831.189 | P15: =E15*((1+D15)^P21*P22+(1+D15)^(P21+1)*P23)/12 -> 79136.125 | Q15: =E15*((1+D15)^Q21*Q22+(1+D15)^(Q21+1)*Q23)/12 -> 81510.208
B16: Effective Annual Rate | G16: =IF(G17=0,0,G15/G17*12) -> 62315 | H16: =IF(H17=0,0,H15/H17*12) -> 62470.787 | I16: =IF(I17=0,0,I15/I17*12) -> 64344.911 | J16: =IF(J17=0,0,J15/J17*12) -> 66275.258 | K16: =IF(K17=0,0,K15/K17*12) -> 68263.516 | L16: =IF(L17=0,0,L15/L17*12) -> 70311.422 | M16: =IF(M17=0,0,M15/M17*12) -> 72420.764 | N16: =IF(N17=0,0,N15/N17*12) -> 74593.387 | ... Q16: =IF(Q17=0,0,Q15/Q17*12) -> 81510.208
B17: Months Worked | G17: =+G20-G19 -> 1 | H17: =+H20-H19 -> 12 | I17: =+I20-I19 -> 12 | J17: =+J20-J19 -> 12 | K17: =+K20-K19 -> 12 | L17: =+L20-L19 -> 12 | M17: =+M20-M19 -> 12 | N17: =+N20-N19 -> 12 | ... Q17: =+Q20-Q19 -> 12
B18: Year Index (n) | G18: 0 | H18: 1 | I18: 2 | J18: 3 | K18: 4 | L18: 5 | M18: 6 | N18: 7 | O18: 8 | P18: 9 | Q18: 10
B19: Service Months @ Yr Start | G19: =MAX(0,12*(G18-1)-C15) -> 0 | H19: =MAX(0,12*(H18-1)-C15) -> 1 | I19: =MAX(0,12*(I18-1)-C15) -> 13 | J19: =MAX(0,12*(J18-1)-C15) -> 25 | K19: =MAX(0,12*(K18-1)-C15) -> 37 | L19: =MAX(0,12*(L18-1)-C15) -> 49 | M19: =MAX(0,12*(M18-1)-C15) -> 61 | N19: =MAX(0,12*(N18-1)-C15) -> 73 | O19: =MAX(0,12*(O18-1)-C15) -> 85 | P19: =MAX(0,12*(P18-1)-C15) -> 97 | Q19: =MAX(0,12*(Q18-1)-C15) -> 109
B20: Service Months @ Yr End | G20: =MAX(0,12*G18-C15) -> 1 | H20: =MAX(0,12*H18-C15) -> 13 | I20: =MAX(0,12*I18-C15) -> 25 | J20: =MAX(0,12*J18-C15) -> 37 | K20: =MAX(0,12*K18-C15) -> 49 | L20: =MAX(0,12*L18-C15) -> 61 | M20: =MAX(0,12*M18-C15) -> 73 | N20: =MAX(0,12*N18-C15) -> 85 | O20: =MAX(0,12*O18-C15) -> 97 | P20: =MAX(0,12*P18-C15) -> 109 | Q20: =MAX(0,12*Q18-C15) -> 121
B21: Completed Service Yrs (k) | G21: =INT(G19/12) -> 0 | H21: =INT(H19/12) -> 0 | I21: =INT(I19/12) -> 1 | J21: =INT(J19/12) -> 2 | K21: =INT(K19/12) -> 3 | L21: =INT(L19/12) -> 4 | M21: =INT(M19/12) -> 5 | N21: =INT(N19/12) -> 6 | ... Q21: =INT(Q19/12) -> 9
B22: Months at Rate k | G22: =MIN(G20,12*(G21+1))-G19 -> 1 | H22: =MIN(H20,12*(H21+1))-H19 -> 11 | I22: =MIN(I20,12*(I21+1))-I19 -> 11 | J22: =MIN(J20,12*(J21+1))-J19 -> 11 | K22: =MIN(K20,12*(K21+1))-K19 -> 11 | L22: =MIN(L20,12*(L21+1))-L19 -> 11 | M22: =MIN(M20,12*(M21+1))-M19 -> 11 | N22: =MIN(N20,12*(N21+1))-N19 -> 11 | ... Q22: =MIN(Q20,12*(Q21+1))-Q19 -> 11
B23: Months at Rate k+1 | G23: =+G20-MIN(G20,12*(G21+1)) -> 0 | H23: =+H20-MIN(H20,12*(H21+1)) -> 1 | I23: =+I20-MIN(I20,12*(I21+1)) -> 1 | J23: =+J20-MIN(J20,12*(J21+1)) -> 1 | K23: =+K20-MIN(K20,12*(K21+1)) -> 1 | L23: =+L20-MIN(L20,12*(L21+1)) -> 1 | M23: =+M20-MIN(M20,12*(M21+1)) -> 1 | N23: =+N20-MIN(N20,12*(N21+1)) -> 1 | ... Q23: =+Q20-MIN(Q20,12*(Q21+1)) -> 1
C25: Start Month | D25: Merit Increase | E25: Base Salary | G25: Year 0 | H25: Year 1 | I25: Year 2 | J25: Year 3 | K25: Year 4 | L25: Year 5 | M25: Year 6 | N25: Year 7 | O25: Year 8 | P25: Year 9 | Q25: Year 10
B26: Salary | C26: -1 | D26: =+Sheet1!$D$43 -> 0.03 | E26: =+Sheet1!$G$48 -> 0 | G26: =E26*((1+D26)^G32*G33+(1+D26)^(G32+1)*G34)/12 -> 0 | H26: =E26*((1+D26)^H32*H33+(1+D26)^(H32+1)*H34)/12 -> 0 | I26: =E26*((1+D26)^I32*I33+(1+D26)^(I32+1)*I34)/12 -> 0 | J26: =E26*((1+D26)^J32*J33+(1+D26)^(J32+1)*J34)/12 -> 0 | K26: =E26*((1+D26)^K32*K33+(1+D26)^(K32+1)*K34)/12 -> 0 | L26: =E26*((1+D26)^L32*L33+(1+D26)^(L32+1)*L34)/12 -> 0 | M26: =E26*((1+D26)^M32*M33+(1+D26)^(M32+1)*M34)/12 -> 0 | N26: =E26*((1+D26)^N32*N33+(1+D26)^(N32+1)*N34)/12 -> 0 | O26: =E26*((1+D26)^O32*O33+(1+D26)^(O32+1)*O34)/12 -> 0 | P26: =E26*((1+D26)^P32*P33+(1+D26)^(P32+1)*P34)/12 -> 0 | Q26: =E26*((1+D26)^Q32*Q33+(1+D26)^(Q32+1)*Q34)/12 -> 0
B27: Effective Annual Rate | G27: =IF(G28=0,0,G26/G28*12) -> 0 | H27: =IF(H28=0,0,H26/H28*12) -> 0 | I27: =IF(I28=0,0,I26/I28*12) -> 0 | J27: =IF(J28=0,0,J26/J28*12) -> 0 | K27: =IF(K28=0,0,K26/K28*12) -> 0 | L27: =IF(L28=0,0,L26/L28*12) -> 0 | M27: =IF(M28=0,0,M26/M28*12) -> 0 | N27: =IF(N28=0,0,N26/N28*12) -> 0 | ... Q27: =IF(Q28=0,0,Q26/Q28*12) -> 0
B28: Months Worked | G28: =+G31-G30 -> 1 | H28: =+H31-H30 -> 12 | I28: =+I31-I30 -> 12 | J28: =+J31-J30 -> 12 | K28: =+K31-K30 -> 12 | L28: =+L31-L30 -> 12 | M28: =+M31-M30 -> 12 | N28: =+N31-N30 -> 12 | ... Q28: =+Q31-Q30 -> 12
B29: Year Index (n) | G29: 0 | H29: 1 | I29: 2 | J29: 3 | K29: 4 | L29: 5 | M29: 6 | N29: 7 | O29: 8 | P29: 9 | Q29: 10
B30: Service Months @ Yr Start | G30: =MAX(0,12*(G29-1)-C26) -> 0 | H30: =MAX(0,12*(H29-1)-C26) -> 1 | I30: =MAX(0,12*(I29-1)-C26) -> 13 | J30: =MAX(0,12*(J29-1)-C26) -> 25 | K30: =MAX(0,12*(K29-1)-C26) -> 37 | L30: =MAX(0,12*(L29-1)-C26) -> 49 | M30: =MAX(0,12*(M29-1)-C26) -> 61 | N30: =MAX(0,12*(N29-1)-C26) -> 73 | O30: =MAX(0,12*(O29-1)-C26) -> 85 | P30: =MAX(0,12*(P29-1)-C26) -> 97 | Q30: =MAX(0,12*(Q29-1)-C26) -> 109
B31: Service Months @ Yr End | G31: =MAX(0,12*G29-C26) -> 1 | H31: =MAX(0,12*H29-C26) -> 13 | I31: =MAX(0,12*I29-C26) -> 25 | J31: =MAX(0,12*J29-C26) -> 37 | K31: =MAX(0,12*K29-C26) -> 49 | L31: =MAX(0,12*L29-C26) -> 61 | M31: =MAX(0,12*M29-C26) -> 73 | N31: =MAX(0,12*N29-C26) -> 85 | O31: =MAX(0,12*O29-C26) -> 97 | P31: =MAX(0,12*P29-C26) -> 109 | Q31: =MAX(0,12*Q29-C26) -> 121
B32: Completed Service Yrs (k) | G32: =INT(G30/12) -> 0 | H32: =INT(H30/12) -> 0 | I32: =INT(I30/12) -> 1 | J32: =INT(J30/12) -> 2 | K32: =INT(K30/12) -> 3 | L32: =INT(L30/12) -> 4 | M32: =INT(M30/12) -> 5 | N32: =INT(N30/12) -> 6 | ... Q32: =INT(Q30/12) -> 9
B33: Months at Rate k | G33: =MIN(G31,12*(G32+1))-G30 -> 1 | H33: =MIN(H31,12*(H32+1))-H30 -> 11 | I33: =MIN(I31,12*(I32+1))-I30 -> 11 | J33: =MIN(J31,12*(J32+1))-J30 -> 11 | K33: =MIN(K31,12*(K32+1))-K30 -> 11 | L33: =MIN(L31,12*(L32+1))-L30 -> 11 | M33: =MIN(M31,12*(M32+1))-M30 -> 11 | N33: =MIN(N31,12*(N32+1))-N30 -> 11 | ... Q33: =MIN(Q31,12*(Q32+1))-Q30 -> 11
B34: Months at Rate k+1 | G34: =+G31-MIN(G31,12*(G32+1)) -> 0 | H34: =+H31-MIN(H31,12*(H32+1)) -> 1 | I34: =+I31-MIN(I31,12*(I32+1)) -> 1 | J34: =+J31-MIN(J31,12*(J32+1)) -> 1 | K34: =+K31-MIN(K31,12*(K32+1)) -> 1 | L34: =+L31-MIN(L31,12*(L32+1)) -> 1 | M34: =+M31-MIN(M31,12*(M32+1)) -> 1 | N34: =+N31-MIN(N31,12*(N32+1)) -> 1 | ... Q34: =+Q31-MIN(Q31,12*(Q32+1)) -> 1
C36: Start Month | D36: Merit Increase | E36: Base Salary | G36: Year 0 | H36: Year 1 | I36: Year 2 | J36: Year 3 | K36: Year 4 | L36: Year 5 | M36: Year 6 | N36: Year 7 | O36: Year 8 | P36: Year 9 | Q36: Year 10
B37: Salary | C37: -1 | D37: =+Sheet1!$D$43 -> 0.03 | E37: =+Sheet1!$G$49 -> 0 | G37: =E37*((1+D37)^G43*G44+(1+D37)^(G43+1)*G45)/12 -> 0 | H37: =E37*((1+D37)^H43*H44+(1+D37)^(H43+1)*H45)/12 -> 0 | I37: =E37*((1+D37)^I43*I44+(1+D37)^(I43+1)*I45)/12 -> 0 | J37: =E37*((1+D37)^J43*J44+(1+D37)^(J43+1)*J45)/12 -> 0 | K37: =E37*((1+D37)^K43*K44+(1+D37)^(K43+1)*K45)/12 -> 0 | L37: =E37*((1+D37)^L43*L44+(1+D37)^(L43+1)*L45)/12 -> 0 | M37: =E37*((1+D37)^M43*M44+(1+D37)^(M43+1)*M45)/12 -> 0 | N37: =E37*((1+D37)^N43*N44+(1+D37)^(N43+1)*N45)/12 -> 0 | O37: =E37*((1+D37)^O43*O44+(1+D37)^(O43+1)*O45)/12 -> 0 | P37: =E37*((1+D37)^P43*P44+(1+D37)^(P43+1)*P45)/12 -> 0 | Q37: =E37*((1+D37)^Q43*Q44+(1+D37)^(Q43+1)*Q45)/12 -> 0
B38: Effective Annual Rate | G38: =IF(G39=0,0,G37/G39*12) -> 0 | H38: =IF(H39=0,0,H37/H39*12) -> 0 | I38: =IF(I39=0,0,I37/I39*12) -> 0 | J38: =IF(J39=0,0,J37/J39*12) -> 0 | K38: =IF(K39=0,0,K37/K39*12) -> 0 | L38: =IF(L39=0,0,L37/L39*12) -> 0 | M38: =IF(M39=0,0,M37/M39*12) -> 0 | N38: =IF(N39=0,0,N37/N39*12) -> 0 | ... Q38: =IF(Q39=0,0,Q37/Q39*12) -> 0
B39: Months Worked | G39: =+G42-G41 -> 1 | H39: =+H42-H41 -> 12 | I39: =+I42-I41 -> 12 | J39: =+J42-J41 -> 12 | K39: =+K42-K41 -> 12 | L39: =+L42-L41 -> 12 | M39: =+M42-M41 -> 12 | N39: =+N42-N41 -> 12 | ... Q39: =+Q42-Q41 -> 12
B40: Year Index (n) | G40: 0 | H40: 1 | I40: 2 | J40: 3 | K40: 4 | L40: 5 | M40: 6 | N40: 7 | O40: 8 | P40: 9 | Q40: 10
B41: Service Months @ Yr Start | G41: =MAX(0,12*(G40-1)-C37) -> 0 | H41: =MAX(0,12*(H40-1)-C37) -> 1 | I41: =MAX(0,12*(I40-1)-C37) -> 13 | J41: =MAX(0,12*(J40-1)-C37) -> 25 | K41: =MAX(0,12*(K40-1)-C37) -> 37 | L41: =MAX(0,12*(L40-1)-C37) -> 49 | M41: =MAX(0,12*(M40-1)-C37) -> 61 | N41: =MAX(0,12*(N40-1)-C37) -> 73 | O41: =MAX(0,12*(O40-1)-C37) -> 85 | P41: =MAX(0,12*(P40-1)-C37) -> 97 | Q41: =MAX(0,12*(Q40-1)-C37) -> 109
B42: Service Months @ Yr End | G42: =MAX(0,12*G40-C37) -> 1 | H42: =MAX(0,12*H40-C37) -> 13 | I42: =MAX(0,12*I40-C37) -> 25 | J42: =MAX(0,12*J40-C37) -> 37 | K42: =MAX(0,12*K40-C37) -> 49 | L42: =MAX(0,12*L40-C37) -> 61 | M42: =MAX(0,12*M40-C37) -> 73 | N42: =MAX(0,12*N40-C37) -> 85 | O42: =MAX(0,12*O40-C37) -> 97 | P42: =MAX(0,12*P40-C37) -> 109 | Q42: =MAX(0,12*Q40-C37) -> 121
B43: Completed Service Yrs (k) | G43: =INT(G41/12) -> 0 | H43: =INT(H41/12) -> 0 | I43: =INT(I41/12) -> 1 | J43: =INT(J41/12) -> 2 | K43: =INT(K41/12) -> 3 | L43: =INT(L41/12) -> 4 | M43: =INT(M41/12) -> 5 | N43: =INT(N41/12) -> 6 | ... Q43: =INT(Q41/12) -> 9
B44: Months at Rate k | G44: =MIN(G42,12*(G43+1))-G41 -> 1 | H44: =MIN(H42,12*(H43+1))-H41 -> 11 | I44: =MIN(I42,12*(I43+1))-I41 -> 11 | J44: =MIN(J42,12*(J43+1))-J41 -> 11 | K44: =MIN(K42,12*(K43+1))-K41 -> 11 | L44: =MIN(L42,12*(L43+1))-L41 -> 11 | M44: =MIN(M42,12*(M43+1))-M41 -> 11 | N44: =MIN(N42,12*(N43+1))-N41 -> 11 | ... Q44: =MIN(Q42,12*(Q43+1))-Q41 -> 11
B45: Months at Rate k+1 | G45: =+G42-MIN(G42,12*(G43+1)) -> 0 | H45: =+H42-MIN(H42,12*(H43+1)) -> 1 | I45: =+I42-MIN(I42,12*(I43+1)) -> 1 | J45: =+J42-MIN(J42,12*(J43+1)) -> 1 | K45: =+K42-MIN(K42,12*(K43+1)) -> 1 | L45: =+L42-MIN(L42,12*(L43+1)) -> 1 | M45: =+M42-MIN(M42,12*(M43+1)) -> 1 | N45: =+N42-MIN(N42,12*(N43+1)) -> 1 | ... Q45: =+Q42-MIN(Q42,12*(Q43+1)) -> 1
C47: Start Month | D47: Merit Increase | E47: Base Salary | G47: Year 0 | H47: Year 1 | I47: Year 2 | J47: Year 3 | K47: Year 4 | L47: Year 5 | M47: Year 6 | N47: Year 7 | O47: Year 8 | P47: Year 9 | Q47: Year 10
B48: Salary | C48: -1 | D48: =+Sheet1!$D$43 -> 0.03 | E48: =+Sheet1!$G$50 -> 0 | G48: =E48*((1+D48)^G54*G55+(1+D48)^(G54+1)*G56)/12 -> 0 | H48: =E48*((1+D48)^H54*H55+(1+D48)^(H54+1)*H56)/12 -> 0 | I48: =E48*((1+D48)^I54*I55+(1+D48)^(I54+1)*I56)/12 -> 0 | J48: =E48*((1+D48)^J54*J55+(1+D48)^(J54+1)*J56)/12 -> 0 | K48: =E48*((1+D48)^K54*K55+(1+D48)^(K54+1)*K56)/12 -> 0 | L48: =E48*((1+D48)^L54*L55+(1+D48)^(L54+1)*L56)/12 -> 0 | M48: =E48*((1+D48)^M54*M55+(1+D48)^(M54+1)*M56)/12 -> 0 | N48: =E48*((1+D48)^N54*N55+(1+D48)^(N54+1)*N56)/12 -> 0 | O48: =E48*((1+D48)^O54*O55+(1+D48)^(O54+1)*O56)/12 -> 0 | P48: =E48*((1+D48)^P54*P55+(1+D48)^(P54+1)*P56)/12 -> 0 | Q48: =E48*((1+D48)^Q54*Q55+(1+D48)^(Q54+1)*Q56)/12 -> 0
B49: Effective Annual Rate | G49: =IF(G50=0,0,G48/G50*12) -> 0 | H49: =IF(H50=0,0,H48/H50*12) -> 0 | I49: =IF(I50=0,0,I48/I50*12) -> 0 | J49: =IF(J50=0,0,J48/J50*12) -> 0 | K49: =IF(K50=0,0,K48/K50*12) -> 0 | L49: =IF(L50=0,0,L48/L50*12) -> 0 | M49: =IF(M50=0,0,M48/M50*12) -> 0 | N49: =IF(N50=0,0,N48/N50*12) -> 0 | ... Q49: =IF(Q50=0,0,Q48/Q50*12) -> 0
B50: Months Worked | G50: =+G53-G52 -> 1 | H50: =+H53-H52 -> 12 | I50: =+I53-I52 -> 12 | J50: =+J53-J52 -> 12 | K50: =+K53-K52 -> 12 | L50: =+L53-L52 -> 12 | M50: =+M53-M52 -> 12 | N50: =+N53-N52 -> 12 | ... Q50: =+Q53-Q52 -> 12
B51: Year Index (n) | G51: 0 | H51: 1 | I51: 2 | J51: 3 | K51: 4 | L51: 5 | M51: 6 | N51: 7 | O51: 8 | P51: 9 | Q51: 10
B52: Service Months @ Yr Start | G52: =MAX(0,12*(G51-1)-C48) -> 0 | H52: =MAX(0,12*(H51-1)-C48) -> 1 | I52: =MAX(0,12*(I51-1)-C48) -> 13 | J52: =MAX(0,12*(J51-1)-C48) -> 25 | K52: =MAX(0,12*(K51-1)-C48) -> 37 | L52: =MAX(0,12*(L51-1)-C48) -> 49 | M52: =MAX(0,12*(M51-1)-C48) -> 61 | N52: =MAX(0,12*(N51-1)-C48) -> 73 | O52: =MAX(0,12*(O51-1)-C48) -> 85 | P52: =MAX(0,12*(P51-1)-C48) -> 97 | Q52: =MAX(0,12*(Q51-1)-C48) -> 109
B53: Service Months @ Yr End | G53: =MAX(0,12*G51-C48) -> 1 | H53: =MAX(0,12*H51-C48) -> 13 | I53: =MAX(0,12*I51-C48) -> 25 | J53: =MAX(0,12*J51-C48) -> 37 | K53: =MAX(0,12*K51-C48) -> 49 | L53: =MAX(0,12*L51-C48) -> 61 | M53: =MAX(0,12*M51-C48) -> 73 | N53: =MAX(0,12*N51-C48) -> 85 | O53: =MAX(0,12*O51-C48) -> 97 | P53: =MAX(0,12*P51-C48) -> 109 | Q53: =MAX(0,12*Q51-C48) -> 121
B54: Completed Service Yrs (k) | G54: =INT(G52/12) -> 0 | H54: =INT(H52/12) -> 0 | I54: =INT(I52/12) -> 1 | J54: =INT(J52/12) -> 2 | K54: =INT(K52/12) -> 3 | L54: =INT(L52/12) -> 4 | M54: =INT(M52/12) -> 5 | N54: =INT(N52/12) -> 6 | ... Q54: =INT(Q52/12) -> 9
B55: Months at Rate k | G55: =MIN(G53,12*(G54+1))-G52 -> 1 | H55: =MIN(H53,12*(H54+1))-H52 -> 11 | I55: =MIN(I53,12*(I54+1))-I52 -> 11 | J55: =MIN(J53,12*(J54+1))-J52 -> 11 | K55: =MIN(K53,12*(K54+1))-K52 -> 11 | L55: =MIN(L53,12*(L54+1))-L52 -> 11 | M55: =MIN(M53,12*(M54+1))-M52 -> 11 | N55: =MIN(N53,12*(N54+1))-N52 -> 11 | ... Q55: =MIN(Q53,12*(Q54+1))-Q52 -> 11
B56: Months at Rate k+1 | G56: =+G53-MIN(G53,12*(G54+1)) -> 0 | H56: =+H53-MIN(H53,12*(H54+1)) -> 1 | I56: =+I53-MIN(I53,12*(I54+1)) -> 1 | J56: =+J53-MIN(J53,12*(J54+1)) -> 1 | K56: =+K53-MIN(K53,12*(K54+1)) -> 1 | L56: =+L53-MIN(L53,12*(L54+1)) -> 1 | M56: =+M53-MIN(M53,12*(M54+1)) -> 1 | N56: =+N53-MIN(N53,12*(N54+1)) -> 1 | ... Q56: =+Q53-MIN(Q53,12*(Q54+1)) -> 1
C58: Start Month | D58: Merit Increase | E58: Base Salary | G58: Year 0 | H58: Year 1 | I58: Year 2 | J58: Year 3 | K58: Year 4 | L58: Year 5 | M58: Year 6 | N58: Year 7 | O58: Year 8 | P58: Year 9 | Q58: Year 10
B59: Salary | C59: -1 | D59: =+Sheet1!$D$43 -> 0.03 | E59: =+Sheet1!$G$51 -> 51744.11 | G59: =E59*((1+D59)^G65*G66+(1+D59)^(G65+1)*G67)/12 -> 4312.0092 | H59: =E59*((1+D59)^H65*H66+(1+D59)^(H65+1)*H67)/12 -> 51873.47 | I59: =E59*((1+D59)^I65*I66+(1+D59)^(I65+1)*I67)/12 -> 53429.674 | J59: =E59*((1+D59)^J65*J66+(1+D59)^(J65+1)*J67)/12 -> 55032.565 | K59: =E59*((1+D59)^K65*K66+(1+D59)^(K65+1)*K67)/12 -> 56683.542 | L59: =E59*((1+D59)^L65*L66+(1+D59)^(L65+1)*L67)/12 -> 58384.048 | M59: =E59*((1+D59)^M65*M66+(1+D59)^(M65+1)*M67)/12 -> 60135.569 | N59: =E59*((1+D59)^N65*N66+(1+D59)^(N65+1)*N67)/12 -> 61939.636 | O59: =E59*((1+D59)^O65*O66+(1+D59)^(O65+1)*O67)/12 -> 63797.825 | P59: =E59*((1+D59)^P65*P66+(1+D59)^(P65+1)*P67)/12 -> 65711.76 | Q59: =E59*((1+D59)^Q65*Q66+(1+D59)^(Q65+1)*Q67)/12 -> 67683.113
B60: Effective Annual Rate | G60: =IF(G61=0,0,G59/G61*12) -> 51744.11 | H60: =IF(H61=0,0,H59/H61*12) -> 51873.47 | I60: =IF(I61=0,0,I59/I61*12) -> 53429.674 | J60: =IF(J61=0,0,J59/J61*12) -> 55032.565 | K60: =IF(K61=0,0,K59/K61*12) -> 56683.542 | L60: =IF(L61=0,0,L59/L61*12) -> 58384.048 | M60: =IF(M61=0,0,M59/M61*12) -> 60135.569 | N60: =IF(N61=0,0,N59/N61*12) -> 61939.636 | ... Q60: =IF(Q61=0,0,Q59/Q61*12) -> 67683.113
B61: Months Worked | G61: =+G64-G63 -> 1 | H61: =+H64-H63 -> 12 | I61: =+I64-I63 -> 12 | J61: =+J64-J63 -> 12 | K61: =+K64-K63 -> 12 | L61: =+L64-L63 -> 12 | M61: =+M64-M63 -> 12 | N61: =+N64-N63 -> 12 | ... Q61: =+Q64-Q63 -> 12
B62: Year Index (n) | G62: 0 | H62: 1 | I62: 2 | J62: 3 | K62: 4 | L62: 5 | M62: 6 | N62: 7 | O62: 8 | P62: 9 | Q62: 10
B63: Service Months @ Yr Start | G63: =MAX(0,12*(G62-1)-C59) -> 0 | H63: =MAX(0,12*(H62-1)-C59) -> 1 | I63: =MAX(0,12*(I62-1)-C59) -> 13 | J63: =MAX(0,12*(J62-1)-C59) -> 25 | K63: =MAX(0,12*(K62-1)-C59) -> 37 | L63: =MAX(0,12*(L62-1)-C59) -> 49 | M63: =MAX(0,12*(M62-1)-C59) -> 61 | N63: =MAX(0,12*(N62-1)-C59) -> 73 | O63: =MAX(0,12*(O62-1)-C59) -> 85 | P63: =MAX(0,12*(P62-1)-C59) -> 97 | Q63: =MAX(0,12*(Q62-1)-C59) -> 109
B64: Service Months @ Yr End | G64: =MAX(0,12*G62-C59) -> 1 | H64: =MAX(0,12*H62-C59) -> 13 | I64: =MAX(0,12*I62-C59) -> 25 | J64: =MAX(0,12*J62-C59) -> 37 | K64: =MAX(0,12*K62-C59) -> 49 | L64: =MAX(0,12*L62-C59) -> 61 | M64: =MAX(0,12*M62-C59) -> 73 | N64: =MAX(0,12*N62-C59) -> 85 | O64: =MAX(0,12*O62-C59) -> 97 | P64: =MAX(0,12*P62-C59) -> 109 | Q64: =MAX(0,12*Q62-C59) -> 121
B65: Completed Service Yrs (k) | G65: =INT(G63/12) -> 0 | H65: =INT(H63/12) -> 0 | I65: =INT(I63/12) -> 1 | J65: =INT(J63/12) -> 2 | K65: =INT(K63/12) -> 3 | L65: =INT(L63/12) -> 4 | M65: =INT(M63/12) -> 5 | N65: =INT(N63/12) -> 6 | ... Q65: =INT(Q63/12) -> 9
B66: Months at Rate k | G66: =MIN(G64,12*(G65+1))-G63 -> 1 | H66: =MIN(H64,12*(H65+1))-H63 -> 11 | I66: =MIN(I64,12*(I65+1))-I63 -> 11 | J66: =MIN(J64,12*(J65+1))-J63 -> 11 | K66: =MIN(K64,12*(K65+1))-K63 -> 11 | L66: =MIN(L64,12*(L65+1))-L63 -> 11 | M66: =MIN(M64,12*(M65+1))-M63 -> 11 | N66: =MIN(N64,12*(N65+1))-N63 -> 11 | ... Q66: =MIN(Q64,12*(Q65+1))-Q63 -> 11
B67: Months at Rate k+1 | G67: =+G64-MIN(G64,12*(G65+1)) -> 0 | H67: =+H64-MIN(H64,12*(H65+1)) -> 1 | I67: =+I64-MIN(I64,12*(I65+1)) -> 1 | J67: =+J64-MIN(J64,12*(J65+1)) -> 1 | K67: =+K64-MIN(K64,12*(K65+1)) -> 1 | L67: =+L64-MIN(L64,12*(L65+1)) -> 1 | M67: =+M64-MIN(M64,12*(M65+1)) -> 1 | N67: =+N64-MIN(N64,12*(N65+1)) -> 1 | ... Q67: =+Q64-MIN(Q64,12*(Q65+1)) -> 1
C69: Start Month | D69: Merit Increase | E69: Base Salary | G69: Year 0 | H69: Year 1 | I69: Year 2 | J69: Year 3 | K69: Year 4 | L69: Year 5 | M69: Year 6 | N69: Year 7 | O69: Year 8 | P69: Year 9 | Q69: Year 10
B70: Salary | C70: -1 | D70: =+Sheet1!$D$43 -> 0.03 | E70: =+Sheet1!$G$52 -> 0 | G70: =E70*((1+D70)^G76*G77+(1+D70)^(G76+1)*G78)/12 -> 0 | H70: =E70*((1+D70)^H76*H77+(1+D70)^(H76+1)*H78)/12 -> 0 | I70: =E70*((1+D70)^I76*I77+(1+D70)^(I76+1)*I78)/12 -> 0 | J70: =E70*((1+D70)^J76*J77+(1+D70)^(J76+1)*J78)/12 -> 0 | K70: =E70*((1+D70)^K76*K77+(1+D70)^(K76+1)*K78)/12 -> 0 | L70: =E70*((1+D70)^L76*L77+(1+D70)^(L76+1)*L78)/12 -> 0 | M70: =E70*((1+D70)^M76*M77+(1+D70)^(M76+1)*M78)/12 -> 0 | N70: =E70*((1+D70)^N76*N77+(1+D70)^(N76+1)*N78)/12 -> 0 | O70: =E70*((1+D70)^O76*O77+(1+D70)^(O76+1)*O78)/12 -> 0 | P70: =E70*((1+D70)^P76*P77+(1+D70)^(P76+1)*P78)/12 -> 0 | Q70: =E70*((1+D70)^Q76*Q77+(1+D70)^(Q76+1)*Q78)/12 -> 0
B71: Effective Annual Rate | G71: =IF(G72=0,0,G70/G72*12) -> 0 | H71: =IF(H72=0,0,H70/H72*12) -> 0 | I71: =IF(I72=0,0,I70/I72*12) -> 0 | J71: =IF(J72=0,0,J70/J72*12) -> 0 | K71: =IF(K72=0,0,K70/K72*12) -> 0 | L71: =IF(L72=0,0,L70/L72*12) -> 0 | M71: =IF(M72=0,0,M70/M72*12) -> 0 | N71: =IF(N72=0,0,N70/N72*12) -> 0 | ... Q71: =IF(Q72=0,0,Q70/Q72*12) -> 0
B72: Months Worked | G72: =+G75-G74 -> 1 | H72: =+H75-H74 -> 12 | I72: =+I75-I74 -> 12 | J72: =+J75-J74 -> 12 | K72: =+K75-K74 -> 12 | L72: =+L75-L74 -> 12 | M72: =+M75-M74 -> 12 | N72: =+N75-N74 -> 12 | ... Q72: =+Q75-Q74 -> 12
B73: Year Index (n) | G73: 0 | H73: 1 | I73: 2 | J73: 3 | K73: 4 | L73: 5 | M73: 6 | N73: 7 | O73: 8 | P73: 9 | Q73: 10
B74: Service Months @ Yr Start | G74: =MAX(0,12*(G73-1)-C70) -> 0 | H74: =MAX(0,12*(H73-1)-C70) -> 1 | I74: =MAX(0,12*(I73-1)-C70) -> 13 | J74: =MAX(0,12*(J73-1)-C70) -> 25 | K74: =MAX(0,12*(K73-1)-C70) -> 37 | L74: =MAX(0,12*(L73-1)-C70) -> 49 | M74: =MAX(0,12*(M73-1)-C70) -> 61 | N74: =MAX(0,12*(N73-1)-C70) -> 73 | O74: =MAX(0,12*(O73-1)-C70) -> 85 | P74: =MAX(0,12*(P73-1)-C70) -> 97 | Q74: =MAX(0,12*(Q73-1)-C70) -> 109
B75: Service Months @ Yr End | G75: =MAX(0,12*G73-C70) -> 1 | H75: =MAX(0,12*H73-C70) -> 13 | I75: =MAX(0,12*I73-C70) -> 25 | J75: =MAX(0,12*J73-C70) -> 37 | K75: =MAX(0,12*K73-C70) -> 49 | L75: =MAX(0,12*L73-C70) -> 61 | M75: =MAX(0,12*M73-C70) -> 73 | N75: =MAX(0,12*N73-C70) -> 85 | O75: =MAX(0,12*O73-C70) -> 97 | P75: =MAX(0,12*P73-C70) -> 109 | Q75: =MAX(0,12*Q73-C70) -> 121
B76: Completed Service Yrs (k) | G76: =INT(G74/12) -> 0 | H76: =INT(H74/12) -> 0 | I76: =INT(I74/12) -> 1 | J76: =INT(J74/12) -> 2 | K76: =INT(K74/12) -> 3 | L76: =INT(L74/12) -> 4 | M76: =INT(M74/12) -> 5 | N76: =INT(N74/12) -> 6 | ... Q76: =INT(Q74/12) -> 9
B77: Months at Rate k | G77: =MIN(G75,12*(G76+1))-G74 -> 1 | H77: =MIN(H75,12*(H76+1))-H74 -> 11 | I77: =MIN(I75,12*(I76+1))-I74 -> 11 | J77: =MIN(J75,12*(J76+1))-J74 -> 11 | K77: =MIN(K75,12*(K76+1))-K74 -> 11 | L77: =MIN(L75,12*(L76+1))-L74 -> 11 | M77: =MIN(M75,12*(M76+1))-M74 -> 11 | N77: =MIN(N75,12*(N76+1))-N74 -> 11 | ... Q77: =MIN(Q75,12*(Q76+1))-Q74 -> 11
B78: Months at Rate k+1 | G78: =+G75-MIN(G75,12*(G76+1)) -> 0 | H78: =+H75-MIN(H75,12*(H76+1)) -> 1 | I78: =+I75-MIN(I75,12*(I76+1)) -> 1 | J78: =+J75-MIN(J75,12*(J76+1)) -> 1 | K78: =+K75-MIN(K75,12*(K76+1)) -> 1 | L78: =+L75-MIN(L75,12*(L76+1)) -> 1 | M78: =+M75-MIN(M75,12*(M76+1)) -> 1 | N78: =+N75-MIN(N75,12*(N76+1)) -> 1 | ... Q78: =+Q75-MIN(Q75,12*(Q76+1)) -> 1
C80: Start Month | D80: Merit Increase | E80: Base Salary | G80: Year 0 | H80: Year 1 | I80: Year 2 | J80: Year 3 | K80: Year 4 | L80: Year 5 | M80: Year 6 | N80: Year 7 | O80: Year 8 | P80: Year 9 | Q80: Year 10
B81: Salary | C81: -1 | D81: =+Sheet1!$D$43 -> 0.03 | E81: =+Sheet1!$G$53 -> 0 | G81: =E81*((1+D81)^G87*G88+(1+D81)^(G87+1)*G89)/12 -> 0 | H81: =E81*((1+D81)^H87*H88+(1+D81)^(H87+1)*H89)/12 -> 0 | I81: =E81*((1+D81)^I87*I88+(1+D81)^(I87+1)*I89)/12 -> 0 | J81: =E81*((1+D81)^J87*J88+(1+D81)^(J87+1)*J89)/12 -> 0 | K81: =E81*((1+D81)^K87*K88+(1+D81)^(K87+1)*K89)/12 -> 0 | L81: =E81*((1+D81)^L87*L88+(1+D81)^(L87+1)*L89)/12 -> 0 | M81: =E81*((1+D81)^M87*M88+(1+D81)^(M87+1)*M89)/12 -> 0 | N81: =E81*((1+D81)^N87*N88+(1+D81)^(N87+1)*N89)/12 -> 0 | O81: =E81*((1+D81)^O87*O88+(1+D81)^(O87+1)*O89)/12 -> 0 | P81: =E81*((1+D81)^P87*P88+(1+D81)^(P87+1)*P89)/12 -> 0 | Q81: =E81*((1+D81)^Q87*Q88+(1+D81)^(Q87+1)*Q89)/12 -> 0
B82: Effective Annual Rate | G82: =IF(G83=0,0,G81/G83*12) -> 0 | H82: =IF(H83=0,0,H81/H83*12) -> 0 | I82: =IF(I83=0,0,I81/I83*12) -> 0 | J82: =IF(J83=0,0,J81/J83*12) -> 0 | K82: =IF(K83=0,0,K81/K83*12) -> 0 | L82: =IF(L83=0,0,L81/L83*12) -> 0 | M82: =IF(M83=0,0,M81/M83*12) -> 0 | N82: =IF(N83=0,0,N81/N83*12) -> 0 | ... Q82: =IF(Q83=0,0,Q81/Q83*12) -> 0
B83: Months Worked | G83: =+G86-G85 -> 1 | H83: =+H86-H85 -> 12 | I83: =+I86-I85 -> 12 | J83: =+J86-J85 -> 12 | K83: =+K86-K85 -> 12 | L83: =+L86-L85 -> 12 | M83: =+M86-M85 -> 12 | N83: =+N86-N85 -> 12 | ... Q83: =+Q86-Q85 -> 12
B84: Year Index (n) | G84: 0 | H84: 1 | I84: 2 | J84: 3 | K84: 4 | L84: 5 | M84: 6 | N84: 7 | O84: 8 | P84: 9 | Q84: 10
B85: Service Months @ Yr Start | G85: =MAX(0,12*(G84-1)-C81) -> 0 | H85: =MAX(0,12*(H84-1)-C81) -> 1 | I85: =MAX(0,12*(I84-1)-C81) -> 13 | J85: =MAX(0,12*(J84-1)-C81) -> 25 | K85: =MAX(0,12*(K84-1)-C81) -> 37 | L85: =MAX(0,12*(L84-1)-C81) -> 49 | M85: =MAX(0,12*(M84-1)-C81) -> 61 | N85: =MAX(0,12*(N84-1)-C81) -> 73 | O85: =MAX(0,12*(O84-1)-C81) -> 85 | P85: =MAX(0,12*(P84-1)-C81) -> 97 | Q85: =MAX(0,12*(Q84-1)-C81) -> 109
B86: Service Months @ Yr End | G86: =MAX(0,12*G84-C81) -> 1 | H86: =MAX(0,12*H84-C81) -> 13 | I86: =MAX(0,12*I84-C81) -> 25 | J86: =MAX(0,12*J84-C81) -> 37 | K86: =MAX(0,12*K84-C81) -> 49 | L86: =MAX(0,12*L84-C81) -> 61 | M86: =MAX(0,12*M84-C81) -> 73 | N86: =MAX(0,12*N84-C81) -> 85 | O86: =MAX(0,12*O84-C81) -> 97 | P86: =MAX(0,12*P84-C81) -> 109 | Q86: =MAX(0,12*Q84-C81) -> 121
B87: Completed Service Yrs (k) | G87: =INT(G85/12) -> 0 | H87: =INT(H85/12) -> 0 | I87: =INT(I85/12) -> 1 | J87: =INT(J85/12) -> 2 | K87: =INT(K85/12) -> 3 | L87: =INT(L85/12) -> 4 | M87: =INT(M85/12) -> 5 | N87: =INT(N85/12) -> 6 | ... Q87: =INT(Q85/12) -> 9
B88: Months at Rate k | G88: =MIN(G86,12*(G87+1))-G85 -> 1 | H88: =MIN(H86,12*(H87+1))-H85 -> 11 | I88: =MIN(I86,12*(I87+1))-I85 -> 11 | J88: =MIN(J86,12*(J87+1))-J85 -> 11 | K88: =MIN(K86,12*(K87+1))-K85 -> 11 | L88: =MIN(L86,12*(L87+1))-L85 -> 11 | M88: =MIN(M86,12*(M87+1))-M85 -> 11 | N88: =MIN(N86,12*(N87+1))-N85 -> 11 | ... Q88: =MIN(Q86,12*(Q87+1))-Q85 -> 11
B89: Months at Rate k+1 | G89: =+G86-MIN(G86,12*(G87+1)) -> 0 | H89: =+H86-MIN(H86,12*(H87+1)) -> 1 | I89: =+I86-MIN(I86,12*(I87+1)) -> 1 | J89: =+J86-MIN(J86,12*(J87+1)) -> 1 | K89: =+K86-MIN(K86,12*(K87+1)) -> 1 | L89: =+L86-MIN(L86,12*(L87+1)) -> 1 | M89: =+M86-MIN(M86,12*(M87+1)) -> 1 | N89: =+N86-MIN(N86,12*(N87+1)) -> 1 | ... Q89: =+Q86-MIN(Q86,12*(Q87+1)) -> 1
C91: Start Month | D91: Merit Increase | E91: Base Salary | G91: Year 0 | H91: Year 1 | I91: Year 2 | J91: Year 3 | K91: Year 4 | L91: Year 5 | M91: Year 6 | N91: Year 7 | O91: Year 8 | P91: Year 9 | Q91: Year 10
B92: Salary | C92: -1 | D92: =+Sheet1!$D$43 -> 0.03 | E92: =+Sheet1!$G$54 -> 0 | G92: =E92*((1+D92)^G98*G99+(1+D92)^(G98+1)*G100)/12 -> 0 | H92: =E92*((1+D92)^H98*H99+(1+D92)^(H98+1)*H100)/12 -> 0 | I92: =E92*((1+D92)^I98*I99+(1+D92)^(I98+1)*I100)/12 -> 0 | J92: =E92*((1+D92)^J98*J99+(1+D92)^(J98+1)*J100)/12 -> 0 | K92: =E92*((1+D92)^K98*K99+(1+D92)^(K98+1)*K100)/12 -> 0 | L92: =E92*((1+D92)^L98*L99+(1+D92)^(L98+1)*L100)/12 -> 0 | M92: =E92*((1+D92)^M98*M99+(1+D92)^(M98+1)*M100)/12 -> 0 | N92: =E92*((1+D92)^N98*N99+(1+D92)^(N98+1)*N100)/12 -> 0 | O92: =E92*((1+D92)^O98*O99+(1+D92)^(O98+1)*O100)/12 -> 0 | P92: =E92*((1+D92)^P98*P99+(1+D92)^(P98+1)*P100)/12 -> 0 | Q92: =E92*((1+D92)^Q98*Q99+(1+D92)^(Q98+1)*Q100)/12 -> 0
B93: Effective Annual Rate | G93: =IF(G94=0,0,G92/G94*12) -> 0 | H93: =IF(H94=0,0,H92/H94*12) -> 0 | I93: =IF(I94=0,0,I92/I94*12) -> 0 | J93: =IF(J94=0,0,J92/J94*12) -> 0 | K93: =IF(K94=0,0,K92/K94*12) -> 0 | L93: =IF(L94=0,0,L92/L94*12) -> 0 | M93: =IF(M94=0,0,M92/M94*12) -> 0 | N93: =IF(N94=0,0,N92/N94*12) -> 0 | ... Q93: =IF(Q94=0,0,Q92/Q94*12) -> 0
B94: Months Worked | G94: =+G97-G96 -> 1 | H94: =+H97-H96 -> 12 | I94: =+I97-I96 -> 12 | J94: =+J97-J96 -> 12 | K94: =+K97-K96 -> 12 | L94: =+L97-L96 -> 12 | M94: =+M97-M96 -> 12 | N94: =+N97-N96 -> 12 | ... Q94: =+Q97-Q96 -> 12
B95: Year Index (n) | G95: 0 | H95: 1 | I95: 2 | J95: 3 | K95: 4 | L95: 5 | M95: 6 | N95: 7 | O95: 8 | P95: 9 | Q95: 10
B96: Service Months @ Yr Start | G96: =MAX(0,12*(G95-1)-C92) -> 0 | H96: =MAX(0,12*(H95-1)-C92) -> 1 | I96: =MAX(0,12*(I95-1)-C92) -> 13 | J96: =MAX(0,12*(J95-1)-C92) -> 25 | K96: =MAX(0,12*(K95-1)-C92) -> 37 | L96: =MAX(0,12*(L95-1)-C92) -> 49 | M96: =MAX(0,12*(M95-1)-C92) -> 61 | N96: =MAX(0,12*(N95-1)-C92) -> 73 | O96: =MAX(0,12*(O95-1)-C92) -> 85 | P96: =MAX(0,12*(P95-1)-C92) -> 97 | Q96: =MAX(0,12*(Q95-1)-C92) -> 109
B97: Service Months @ Yr End | G97: =MAX(0,12*G95-C92) -> 1 | H97: =MAX(0,12*H95-C92) -> 13 | I97: =MAX(0,12*I95-C92) -> 25 | J97: =MAX(0,12*J95-C92) -> 37 | K97: =MAX(0,12*K95-C92) -> 49 | L97: =MAX(0,12*L95-C92) -> 61 | M97: =MAX(0,12*M95-C92) -> 73 | N97: =MAX(0,12*N95-C92) -> 85 | O97: =MAX(0,12*O95-C92) -> 97 | P97: =MAX(0,12*P95-C92) -> 109 | Q97: =MAX(0,12*Q95-C92) -> 121
B98: Completed Service Yrs (k) | G98: =INT(G96/12) -> 0 | H98: =INT(H96/12) -> 0 | I98: =INT(I96/12) -> 1 | J98: =INT(J96/12) -> 2 | K98: =INT(K96/12) -> 3 | L98: =INT(L96/12) -> 4 | M98: =INT(M96/12) -> 5 | N98: =INT(N96/12) -> 6 | ... Q98: =INT(Q96/12) -> 9
B99: Months at Rate k | G99: =MIN(G97,12*(G98+1))-G96 -> 1 | H99: =MIN(H97,12*(H98+1))-H96 -> 11 | I99: =MIN(I97,12*(I98+1))-I96 -> 11 | J99: =MIN(J97,12*(J98+1))-J96 -> 11 | K99: =MIN(K97,12*(K98+1))-K96 -> 11 | L99: =MIN(L97,12*(L98+1))-L96 -> 11 | M99: =MIN(M97,12*(M98+1))-M96 -> 11 | N99: =MIN(N97,12*(N98+1))-N96 -> 11 | ... Q99: =MIN(Q97,12*(Q98+1))-Q96 -> 11
B100: Months at Rate k+1 | G100: =+G97-MIN(G97,12*(G98+1)) -> 0 | H100: =+H97-MIN(H97,12*(H98+1)) -> 1 | I100: =+I97-MIN(I97,12*(I98+1)) -> 1 | J100: =+J97-MIN(J97,12*(J98+1)) -> 1 | K100: =+K97-MIN(K97,12*(K98+1)) -> 1 | L100: =+L97-MIN(L97,12*(L98+1)) -> 1 | M100: =+M97-MIN(M97,12*(M98+1)) -> 1 | N100: =+N97-MIN(N97,12*(N98+1)) -> 1 | ... Q100: =+Q97-MIN(Q97,12*(Q98+1)) -> 1
C102: Start Month | D102: Merit Increase | E102: Base Salary | G102: Year 0 | H102: Year 1 | I102: Year 2 | J102: Year 3 | K102: Year 4 | L102: Year 5 | M102: Year 6 | N102: Year 7 | O102: Year 8 | P102: Year 9 | Q102: Year 10
B103: Salary | C103: -1 | D103: =+Sheet1!$D$43 -> 0.03 | E103: =+Sheet1!$G$55 -> 0 | G103: =E103*((1+D103)^G109*G110+(1+D103)^(G109+1)*G111)/12 -> 0 | H103: =E103*((1+D103)^H109*H110+(1+D103)^(H109+1)*H111)/12 -> 0 | I103: =E103*((1+D103)^I109*I110+(1+D103)^(I109+1)*I111)/12 -> 0 | J103: =E103*((1+D103)^J109*J110+(1+D103)^(J109+1)*J111)/12 -> 0 | K103: =E103*((1+D103)^K109*K110+(1+D103)^(K109+1)*K111)/12 -> 0 | L103: =E103*((1+D103)^L109*L110+(1+D103)^(L109+1)*L111)/12 -> 0 | M103: =E103*((1+D103)^M109*M110+(1+D103)^(M109+1)*M111)/12 -> 0 | N103: =E103*((1+D103)^N109*N110+(1+D103)^(N109+1)*N111)/12 -> 0 | O103: =E103*((1+D103)^O109*O110+(1+D103)^(O109+1)*O111)/12 -> 0 | P103: =E103*((1+D103)^P109*P110+(1+D103)^(P109+1)*P111)/12 -> 0 | Q103: =E103*((1+D103)^Q109*Q110+(1+D103)^(Q109+1)*Q111)/12 -> 0
B104: Effective Annual Rate | G104: =IF(G105=0,0,G103/G105*12) -> 0 | H104: =IF(H105=0,0,H103/H105*12) -> 0 | I104: =IF(I105=0,0,I103/I105*12) -> 0 | J104: =IF(J105=0,0,J103/J105*12) -> 0 | K104: =IF(K105=0,0,K103/K105*12) -> 0 | L104: =IF(L105=0,0,L103/L105*12) -> 0 | M104: =IF(M105=0,0,M103/M105*12) -> 0 | N104: =IF(N105=0,0,N103/N105*12) -> 0 | ... Q104: =IF(Q105=0,0,Q103/Q105*12) -> 0
B105: Months Worked | G105: =+G108-G107 -> 1 | H105: =+H108-H107 -> 12 | I105: =+I108-I107 -> 12 | J105: =+J108-J107 -> 12 | K105: =+K108-K107 -> 12 | L105: =+L108-L107 -> 12 | M105: =+M108-M107 -> 12 | N105: =+N108-N107 -> 12 | ... Q105: =+Q108-Q107 -> 12
B106: Year Index (n) | G106: 0 | H106: 1 | I106: 2 | J106: 3 | K106: 4 | L106: 5 | M106: 6 | N106: 7 | O106: 8 | P106: 9 | Q106: 10
B107: Service Months @ Yr Start | G107: =MAX(0,12*(G106-1)-C103) -> 0 | H107: =MAX(0,12*(H106-1)-C103) -> 1 | I107: =MAX(0,12*(I106-1)-C103) -> 13 | J107: =MAX(0,12*(J106-1)-C103) -> 25 | K107: =MAX(0,12*(K106-1)-C103) -> 37 | L107: =MAX(0,12*(L106-1)-C103) -> 49 | M107: =MAX(0,12*(M106-1)-C103) -> 61 | N107: =MAX(0,12*(N106-1)-C103) -> 73 | O107: =MAX(0,12*(O106-1)-C103) -> 85 | P107: =MAX(0,12*(P106-1)-C103) -> 97 | Q107: =MAX(0,12*(Q106-1)-C103) -> 109
B108: Service Months @ Yr End | G108: =MAX(0,12*G106-C103) -> 1 | H108: =MAX(0,12*H106-C103) -> 13 | I108: =MAX(0,12*I106-C103) -> 25 | J108: =MAX(0,12*J106-C103) -> 37 | K108: =MAX(0,12*K106-C103) -> 49 | L108: =MAX(0,12*L106-C103) -> 61 | M108: =MAX(0,12*M106-C103) -> 73 | N108: =MAX(0,12*N106-C103) -> 85 | O108: =MAX(0,12*O106-C103) -> 97 | P108: =MAX(0,12*P106-C103) -> 109 | Q108: =MAX(0,12*Q106-C103) -> 121
B109: Completed Service Yrs (k) | G109: =INT(G107/12) -> 0 | H109: =INT(H107/12) -> 0 | I109: =INT(I107/12) -> 1 | J109: =INT(J107/12) -> 2 | K109: =INT(K107/12) -> 3 | L109: =INT(L107/12) -> 4 | M109: =INT(M107/12) -> 5 | N109: =INT(N107/12) -> 6 | ... Q109: =INT(Q107/12) -> 9
B110: Months at Rate k | G110: =MIN(G108,12*(G109+1))-G107 -> 1 | H110: =MIN(H108,12*(H109+1))-H107 -> 11 | I110: =MIN(I108,12*(I109+1))-I107 -> 11 | J110: =MIN(J108,12*(J109+1))-J107 -> 11 | K110: =MIN(K108,12*(K109+1))-K107 -> 11 | L110: =MIN(L108,12*(L109+1))-L107 -> 11 | M110: =MIN(M108,12*(M109+1))-M107 -> 11 | N110: =MIN(N108,12*(N109+1))-N107 -> 11 | ... Q110: =MIN(Q108,12*(Q109+1))-Q107 -> 11
B111: Months at Rate k+1 | G111: =+G108-MIN(G108,12*(G109+1)) -> 0 | H111: =+H108-MIN(H108,12*(H109+1)) -> 1 | I111: =+I108-MIN(I108,12*(I109+1)) -> 1 | J111: =+J108-MIN(J108,12*(J109+1)) -> 1 | K111: =+K108-MIN(K108,12*(K109+1)) -> 1 | L111: =+L108-MIN(L108,12*(L109+1)) -> 1 | M111: =+M108-MIN(M108,12*(M109+1)) -> 1 | N111: =+N108-MIN(N108,12*(N109+1)) -> 1 | ... Q111: =+Q108-MIN(Q108,12*(Q109+1)) -> 1
...
